{
    "suites":[
        "components/uni-date-picker/test",
        "components/uni-form-item/test",
        "components/uni-form-item-group/test",
        "components/uni-data-table/test"
    ],
    "plugins": {
        "local": {
            "browsers": ["chrome", "firefox"]
        },
        "sauce": {
            "browsers": [{
                "browserName": "microsoftedge",
                "platform": "Windows 10"
            }, {
                "browserName": "safari",
                "platform": "macOS 10.13",
                "version": "latest"
            }]
        }
    }
}
